epygame/__init__.py
epygame/shadowMaker.py
epygame/utils.py
epygame/android/__init__.py
epygame/android/graphics/Bitmap.py
epygame/android/graphics/Canvas.py
epygame/android/graphics/Color.py
epygame/android/graphics/Paint.py
epygame/android/graphics/Path.py
epygame/android/graphics/Point.py
epygame/android/graphics/Rect.py
epygame/android/graphics/Typeface.py
epygame/android/graphics/__init__.py
epygame/android/graphics/drawable/Drawable.py
epygame/android/graphics/drawable/__init__.py
epygame/android/media/MediaPlayer.py
epygame/android/media/__init__.py
epygame/android/text/TextPaint.py
epygame/android/text/__init__.py
epygame/android/view/Display.py
epygame/android/view/Gravity.py
epygame/android/view/View.py
epygame/android/view/ViewGroup.py
epygame/android/view/__init__.py
epygame/android/widget/Button.py
epygame/android/widget/FrameLayout.py
epygame/android/widget/LinearLayout.py
epygame/android/widget/TextView.py
epygame/android/widget/__init__.py
epygame/window/App.py
epygame/window/__init__.py
epygame-0.0.1.dist-info/LICENSE
epygame-0.0.1.dist-info/METADATA
epygame-0.0.1.dist-info/WHEEL
epygame-0.0.1.dist-info/top_level.txt
epygame-0.0.1.dist-info/RECORD
