Metadata-Version: 2.1
Name: epygame
Version: 0.0.1
Summary: A library for Python using android classes based on the pygame library
Home-page: https://github.com/Ethosa/epygame
Author: Ethosa
Author-email: ethosa.pygame@gmail.com
License: UNKNOWN
Platform: UNKNOWN
Classifier: Programming Language :: Python :: 3
Classifier: License :: OSI Approved :: MIT License
Classifier: Operating System :: OS Independent
Requires-Dist: pygame
Requires-Dist: requests
